Metadata-Version: 1.1
Name: FigmaPy
Version: 2018.1.0
Summary: Figma API wrapper.
Home-page: https://www.IamGregAmato.com
Author: Greg Amato
Author-email: amatobahn@gmail.com
License: Apache License v2.0
Keywords: Amatobahn,Figma,pypi,package
Platform: UNKNOWN
Classifier: Development Status :: 4 - Beta
Classifier: Intended Audience :: Developers
Classifier: Topic :: Software Development :: Libraries :: Python Modules
Classifier: License :: OSI Approved :: Apache Software License
Classifier: Programming Language :: Python :: 3 :: Only
